honeybee_ies/__init__.py
honeybee_ies/__main__.py
honeybee_ies/_extend_honeybee.py
honeybee_ies/reader.py
honeybee_ies/templates.py
honeybee_ies/types.py
honeybee_ies/writer.py
honeybee_ies/cli/__init__.py
honeybee_ies/cli/translate.py
honeybee_ies/properties/__init__.py
honeybee_ies/properties/model.py
honeybee_ies-0.14.3.dist-info/licenses/LICENSE
honeybee_ies-0.14.3.dist-info/METADATA
honeybee_ies-0.14.3.dist-info/WHEEL
honeybee_ies-0.14.3.dist-info/entry_points.txt
honeybee_ies-0.14.3.dist-info/top_level.txt
honeybee_ies-0.14.3.dist-info/RECORD
